coordinate_parser/__init__.py
coordinate_parser/parser.py
coordinate_parser/py.typed
coordinate_parser-0.1.1.dist-info/METADATA
coordinate_parser-0.1.1.dist-info/WHEEL
coordinate_parser-0.1.1.dist-info/licenses/LICENSE
coordinate_parser-0.1.1.dist-info/RECORD
