Metadata-Version: 2.4
Name: coordinate-parser
Version: 0.1.1
Summary: A Python library for parsing geographic coordinates in various formats
Project-URL: Homepage, https://github.com/17swifts/coordinate-parser
Project-URL: Repository, https://github.com/17swifts/coordinate-parser
Project-URL: Issues, https://github.com/17swifts/coordinate-parser/issues
Project-URL: Documentation, https://github.com/17swifts/coordinate-parser#readme
Author-email: Samantha Swift <s.swift@marcura.com>
Maintainer-email: Samantha Swift <s.swift@marcura.com>
License-Expression: MIT
License-File: LICENSE
Keywords: coordinates,gis,latitude,longitude,maritime,parsing
Classifier: Development Status :: 4 - Beta
Classifier: Intended Audience :: Developers
Classifier: License :: OSI Approved :: MIT License
Classifier: Operating System :: OS Independent
Classifier: Programming Language :: Python :: 3
Classifier: Programming Language :: Python :: 3.11
Classifier: Programming Language :: Python :: 3.12
Classifier: Programming Language :: Python :: 3.13
Classifier: Topic :: Scientific/Engineering :: GIS
Classifier: Topic :: Software Development :: Libraries :: Python Modules
Classifier: Topic :: Text Processing :: Filters
Classifier: Typing :: Typed
Requires-Python: >=3.11
Provides-Extra: dev
Requires-Dist: black>=23.0; extra == 'dev'
Requires-Dist: mypy>=1.0; extra == 'dev'
Requires-Dist: pre-commit>=3.0; extra == 'dev'
Requires-Dist: pytest-cov>=4.0; extra == 'dev'
Requires-Dist: pytest>=7.0; extra == 'dev'
Requires-Dist: ruff>=0.1.0; extra == 'dev'
Provides-Extra: test
Requires-Dist: pytest-cov>=4.0; extra == 'test'
Requires-Dist: pytest>=7.0; extra == 'test'
